tsx/__init__.py
tsx/ts.py
tsx-0.2.17.dist-info/licenses/LICENSE
tsx-0.2.17.dist-info/METADATA
tsx-0.2.17.dist-info/WHEEL
tsx-0.2.17.dist-info/top_level.txt
tsx-0.2.17.dist-info/RECORD
