Metadata-Version: 2.4
Name: tsx
Version: 0.2.17
Summary: TimeStamp eXtensions for Python
Home-page: https://github.com/asuiu/tsx
Author: Andrei Suiu
Author-email: andrei.suiu@gmail.com
License: GPL
Keywords: timestamp time date datetime ISO 8601
Classifier: Development Status :: 5 - Production/Stable
Classifier: Intended Audience :: Developers
Classifier: Topic :: System :: Logging
Classifier: Topic :: Software Development :: Libraries
Classifier: Topic :: Internet :: Log Analysis
Classifier: License :: OSI Approved :: Apache Software License
Classifier: Programming Language :: Python :: 3.10
Classifier: Programming Language :: Python :: 3.11
Classifier: Programming Language :: Python :: 3.12
Classifier: Programming Language :: Python :: 3.13
Classifier: Programming Language :: Python :: 3.14
Classifier: Programming Language :: Python :: Implementation :: CPython
Classifier: Programming Language :: Python :: Implementation :: PyPy
License-File: LICENSE
Requires-Dist: typing-extensions>=3.7.4; python_version < "3.8"
Requires-Dist: python-dateutil>=2.8.2
Requires-Dist: pytz>=2020.1
Requires-Dist: ciso8601>=2.3.1
Requires-Dist: numpy>=1.8.0
Dynamic: author
Dynamic: author-email
Dynamic: classifier
Dynamic: description
Dynamic: description-content-type
Dynamic: home-page
Dynamic: keywords
Dynamic: license
Dynamic: license-file
Dynamic: requires-dist
Dynamic: summary
